dumpster/__init__.py
dumpster/model.py
dumpster/storage.py
dumpster/test_.py
dumpster/utils.py
dumpster/registries/__init__.py
dumpster/registries/base.py
dumpster/registries/file.py
dumpster/registries/storage.py
dumpster-0.1a0.dist-info/METADATA
dumpster-0.1a0.dist-info/WHEEL
dumpster-0.1a0.dist-info/top_level.txt
dumpster-0.1a0.dist-info/RECORD
