Metadata-Version: 2.1
Name: dumpster
Version: 0.1a0
Summary: UNKNOWN
Home-page: https://www.ritchievink.com
Author: Ritchie Vink
Author-email: ritchie46@gmail.com
License: UNKNOWN
Platform: UNKNOWN
Requires-Python: >=3.6
Requires-Dist: google-cloud-storage (>=1.20.0)
